autoreduce_webapp/__init__.py
autoreduce_webapp/clear_db_objects.py
autoreduce_webapp/manage.py
autoreduce_webapp/autoreduce_django/__init__.py
autoreduce_webapp/autoreduce_django/admin.py
autoreduce_webapp/autoreduce_django/backends.py
autoreduce_webapp/autoreduce_django/context_processors.py
autoreduce_webapp/autoreduce_django/icat_cache.py
autoreduce_webapp/autoreduce_django/icat_communication.py
autoreduce_webapp/autoreduce_django/models.py
autoreduce_webapp/autoreduce_django/settings.py
autoreduce_webapp/autoreduce_django/uows_client.py
autoreduce_webapp/autoreduce_django/urls.py
autoreduce_webapp/autoreduce_django/view_utils.py
autoreduce_webapp/autoreduce_django/views.py
autoreduce_webapp/autoreduce_django/wsgi.py
autoreduce_webapp/autoreduce_django/management/__init__.py
autoreduce_webapp/autoreduce_django/management/commands/__init__.py
autoreduce_webapp/autoreduce_django/management/commands/add_super.py
autoreduce_webapp/autoreduce_django/migrations/0001_initial.py
autoreduce_webapp/autoreduce_django/migrations/__init__.py
autoreduce_webapp/autoreduce_django/templatetags/__init__.py
autoreduce_webapp/autoreduce_django/templatetags/colour_table_rows.py
autoreduce_webapp/autoreduce_django/templatetags/common_helpers.py
autoreduce_webapp/autoreduce_django/templatetags/natural_time_difference.py
autoreduce_webapp/autoreduce_django/templatetags/replace.py
autoreduce_webapp/autoreduce_django/templatetags/variable_type.py
autoreduce_webapp/autoreduce_django/templatetags/view.py
autoreduce_webapp/instrument/__init__.py
autoreduce_webapp/instrument/admin.py
autoreduce_webapp/instrument/urls.py
autoreduce_webapp/instrument/views/__init__.py
autoreduce_webapp/instrument/views/pause.py
autoreduce_webapp/instrument/views/runs.py
autoreduce_webapp/instrument/views/variables.py
autoreduce_webapp/plotting/__init__.py
autoreduce_webapp/plotting/plot_handler.py
autoreduce_webapp/plotting/tests/__init__.py
autoreduce_webapp/plotting/tests/test_plot_handler.py
autoreduce_webapp-21.1.4.dist-info/LICENSE.txt
autoreduce_webapp-21.1.4.dist-info/METADATA
autoreduce_webapp-21.1.4.dist-info/WHEEL
autoreduce_webapp-21.1.4.dist-info/entry_points.txt
autoreduce_webapp-21.1.4.dist-info/top_level.txt
autoreduce_webapp-21.1.4.dist-info/RECORD
